{"bogi":{"appointment":[{"doctor":{"appointment":[],"Appointment":[],"PName":"Marko","Surname":"Pantelic","Email":"pantela@zdravo.com","DateOfBirth":"2021-03-28T17:46:35.3545617+02:00","PhoneNumber":"063/789789","Username":"pantela","ParentsName":"Jovo","MaritalStatus":1,"Gender":0,"Address":null,"PersonID":null},"appointmentRoom":{"appointment":[{"patient":{"appointment":[],"operation":[],"IsGuest":false,"HealthCardNumber":"12123434","Appointment":[],"Operation":[],"PName":"Dejan","Surname":"Bodiroga","Email":"boga@zdravo.com","DateOfBirth":"2021-03-28T17:39:40.5116867+02:00","PhoneNumber":"063/789789","Username":"bogi","ParentsName":"Sale","MaritalStatus":1,"Gender":0,"Address":null,"PersonID":"12345678901"},"doctor":{"appointment":[],"Appointment":[],"PName":"Marko","Surname":"Pantelic","Email":"pantela@zdravo.com","DateOfBirth":"2021-03-28T17:39:40.5105922+02:00","PhoneNumber":"063/789789","Username":"pantela","ParentsName":"Jovo","MaritalStatus":1,"Gender":0,"Address":null,"PersonID":null},"Patient":{"appointment":[],"operation":[],"IsGuest":false,"HealthCardNumber":"12123434","Appointment":[],"Operation":[],"PName":"Dejan","Surname":"Bodiroga","Email":"boga@zdravo.com","DateOfBirth":"2021-03-28T17:39:40.5116867+02:00","PhoneNumber":"063/789789","Username":"bogi","ParentsName":"Sale","MaritalStatus":1,"Gender":0,"Address":null,"PersonID":"12345678901"},"Doctor":{"appointment":[],"Appointment":[],"PName":"Marko","Surname":"Pantelic","Email":"pantela@zdravo.com","DateOfBirth":"2021-03-28T17:39:40.5105922+02:00","PhoneNumber":"063/789789","Username":"pantela","ParentsName":"Jovo","MaritalStatus":1,"Gender":0,"Address":null,"PersonID":null},"StartTime":"2021-03-30T12:00:00Z","Duration":30,"PeriodType":0}],"equipment":[],"Appointment":[{"patient":{"appointment":[],"operation":[],"IsGuest":false,"HealthCardNumber":"12123434","Appointment":[],"Operation":[],"PName":"Dejan","Surname":"Bodiroga","Email":"boga@zdravo.com","DateOfBirth":"2021-03-28T17:39:40.5116867+02:00","PhoneNumber":"063/789789","Username":"bogi","ParentsName":"Sale","MaritalStatus":1,"Gender":0,"Address":null,"PersonID":"12345678901"},"doctor":{"appointment":[],"Appointment":[],"PName":"Marko","Surname":"Pantelic","Email":"pantela@zdravo.com","DateOfBirth":"2021-03-28T17:39:40.5105922+02:00","PhoneNumber":"063/789789","Username":"pantela","ParentsName":"Jovo","MaritalStatus":1,"Gender":0,"Address":null,"PersonID":null},"Patient":{"appointment":[],"operation":[],"IsGuest":false,"HealthCardNumber":"12123434","Appointment":[],"Operation":[],"PName":"Dejan","Surname":"Bodiroga","Email":"boga@zdravo.com","DateOfBirth":"2021-03-28T17:39:40.5116867+02:00","PhoneNumber":"063/789789","Username":"bogi","ParentsName":"Sale","MaritalStatus":1,"Gender":0,"Address":null,"PersonID":"12345678901"},"Doctor":{"appointment":[],"Appointment":[],"PName":"Marko","Surname":"Pantelic","Email":"pantela@zdravo.com","DateOfBirth":"2021-03-28T17:39:40.5105922+02:00","PhoneNumber":"063/789789","Username":"pantela","ParentsName":"Jovo","MaritalStatus":1,"Gender":0,"Address":null,"PersonID":null},"StartTime":"2021-03-30T12:00:00Z","Duration":30,"PeriodType":0}],"RoomType":0,"Id":101,"Name":"soba za pregled - 1","Avaliabe":true,"AvaliableText":"Yes","RoomTypeText":"Appointment","Equipment":[]},"Doctor":{"appointment":[],"Appointment":[],"PName":"Marko","Surname":"Pantelic","Email":"pantela@zdravo.com","DateOfBirth":"2021-03-28T17:46:35.3545617+02:00","PhoneNumber":"063/789789","Username":"pantela","ParentsName":"Jovo","MaritalStatus":1,"Gender":0,"Address":null,"PersonID":null},"AppointmentRoom":{"appointment":[{"patient":{"appointment":[],"operation":[],"IsGuest":false,"HealthCardNumber":"12123434","Appointment":[],"Operation":[],"PName":"Dejan","Surname":"Bodiroga","Email":"boga@zdravo.com","DateOfBirth":"2021-03-28T17:39:40.5116867+02:00","PhoneNumber":"063/789789","Username":"bogi","ParentsName":"Sale","MaritalStatus":1,"Gender":0,"Address":null,"PersonID":"12345678901"},"doctor":{"appointment":[],"Appointment":[],"PName":"Marko","Surname":"Pantelic","Email":"pantela@zdravo.com","DateOfBirth":"2021-03-28T17:39:40.5105922+02:00","PhoneNumber":"063/789789","Username":"pantela","ParentsName":"Jovo","MaritalStatus":1,"Gender":0,"Address":null,"PersonID":null},"Patient":{"appointment":[],"operation":[],"IsGuest":false,"HealthCardNumber":"12123434","Appointment":[],"Operation":[],"PName":"Dejan","Surname":"Bodiroga","Email":"boga@zdravo.com","DateOfBirth":"2021-03-28T17:39:40.5116867+02:00","PhoneNumber":"063/789789","Username":"bogi","ParentsName":"Sale","MaritalStatus":1,"Gender":0,"Address":null,"PersonID":"12345678901"},"Doctor":{"appointment":[],"Appointment":[],"PName":"Marko","Surname":"Pantelic","Email":"pantela@zdravo.com","DateOfBirth":"2021-03-28T17:39:40.5105922+02:00","PhoneNumber":"063/789789","Username":"pantela","ParentsName":"Jovo","MaritalStatus":1,"Gender":0,"Address":null,"PersonID":null},"StartTime":"2021-03-30T12:00:00Z","Duration":30,"PeriodType":0}],"equipment":[],"Appointment":[{"patient":{"appointment":[],"operation":[],"IsGuest":false,"HealthCardNumber":"12123434","Appointment":[],"Operation":[],"PName":"Dejan","Surname":"Bodiroga","Email":"boga@zdravo.com","DateOfBirth":"2021-03-28T17:39:40.5116867+02:00","PhoneNumber":"063/789789","Username":"bogi","ParentsName":"Sale","MaritalStatus":1,"Gender":0,"Address":null,"PersonID":"12345678901"},"doctor":{"appointment":[],"Appointment":[],"PName":"Marko","Surname":"Pantelic","Email":"pantela@zdravo.com","DateOfBirth":"2021-03-28T17:39:40.5105922+02:00","PhoneNumber":"063/789789","Username":"pantela","ParentsName":"Jovo","MaritalStatus":1,"Gender":0,"Address":null,"PersonID":null},"Patient":{"appointment":[],"operation":[],"IsGuest":false,"HealthCardNumber":"12123434","Appointment":[],"Operation":[],"PName":"Dejan","Surname":"Bodiroga","Email":"boga@zdravo.com","DateOfBirth":"2021-03-28T17:39:40.5116867+02:00","PhoneNumber":"063/789789","Username":"bogi","ParentsName":"Sale","MaritalStatus":1,"Gender":0,"Address":null,"PersonID":"12345678901"},"Doctor":{"appointment":[],"Appointment":[],"PName":"Marko","Surname":"Pantelic","Email":"pantela@zdravo.com","DateOfBirth":"2021-03-28T17:39:40.5105922+02:00","PhoneNumber":"063/789789","Username":"pantela","ParentsName":"Jovo","MaritalStatus":1,"Gender":0,"Address":null,"PersonID":null},"StartTime":"2021-03-30T12:00:00Z","Duration":30,"PeriodType":0}],"RoomType":0,"Id":101,"Name":"soba za pregled - 1","Avaliabe":true,"AvaliableText":"Yes","RoomTypeText":"Appointment","Equipment":[]},"StartTime":"2021-04-07T12:00:00Z","Duration":30,"PeriodType":0}],"operation":[],"IsGuest":false,"HealthCardNumber":"12123434","Appointment":[{"doctor":{"appointment":[],"Appointment":[],"PName":"Marko","Surname":"Pantelic","Email":"pantela@zdravo.com","DateOfBirth":"2021-03-28T17:46:35.3545617+02:00","PhoneNumber":"063/789789","Username":"pantela","ParentsName":"Jovo","MaritalStatus":1,"Gender":0,"Address":null,"PersonID":null},"appointmentRoom":{"appointment":[{"patient":{"appointment":[],"operation":[],"IsGuest":false,"HealthCardNumber":"12123434","Appointment":[],"Operation":[],"PName":"Dejan","Surname":"Bodiroga","Email":"boga@zdravo.com","DateOfBirth":"2021-03-28T17:39:40.5116867+02:00","PhoneNumber":"063/789789","Username":"bogi","ParentsName":"Sale","MaritalStatus":1,"Gender":0,"Address":null,"PersonID":"12345678901"},"doctor":{"appointment":[],"Appointment":[],"PName":"Marko","Surname":"Pantelic","Email":"pantela@zdravo.com","DateOfBirth":"2021-03-28T17:39:40.5105922+02:00","PhoneNumber":"063/789789","Username":"pantela","ParentsName":"Jovo","MaritalStatus":1,"Gender":0,"Address":null,"PersonID":null},"Patient":{"appointment":[],"operation":[],"IsGuest":false,"HealthCardNumber":"12123434","Appointment":[],"Operation":[],"PName":"Dejan","Surname":"Bodiroga","Email":"boga@zdravo.com","DateOfBirth":"2021-03-28T17:39:40.5116867+02:00","PhoneNumber":"063/789789","Username":"bogi","ParentsName":"Sale","MaritalStatus":1,"Gender":0,"Address":null,"PersonID":"12345678901"},"Doctor":{"appointment":[],"Appointment":[],"PName":"Marko","Surname":"Pantelic","Email":"pantela@zdravo.com","DateOfBirth":"2021-03-28T17:39:40.5105922+02:00","PhoneNumber":"063/789789","Username":"pantela","ParentsName":"Jovo","MaritalStatus":1,"Gender":0,"Address":null,"PersonID":null},"StartTime":"2021-03-30T12:00:00Z","Duration":30,"PeriodType":0}],"equipment":[],"Appointment":[{"patient":{"appointment":[],"operation":[],"IsGuest":false,"HealthCardNumber":"12123434","Appointment":[],"Operation":[],"PName":"Dejan","Surname":"Bodiroga","Email":"boga@zdravo.com","DateOfBirth":"2021-03-28T17:39:40.5116867+02:00","PhoneNumber":"063/789789","Username":"bogi","ParentsName":"Sale","MaritalStatus":1,"Gender":0,"Address":null,"PersonID":"12345678901"},"doctor":{"appointment":[],"Appointment":[],"PName":"Marko","Surname":"Pantelic","Email":"pantela@zdravo.com","DateOfBirth":"2021-03-28T17:39:40.5105922+02:00","PhoneNumber":"063/789789","Username":"pantela","ParentsName":"Jovo","MaritalStatus":1,"Gender":0,"Address":null,"PersonID":null},"Patient":{"appointment":[],"operation":[],"IsGuest":false,"HealthCardNumber":"12123434","Appointment":[],"Operation":[],"PName":"Dejan","Surname":"Bodiroga","Email":"boga@zdravo.com","DateOfBirth":"2021-03-28T17:39:40.5116867+02:00","PhoneNumber":"063/789789","Username":"bogi","ParentsName":"Sale","MaritalStatus":1,"Gender":0,"Address":null,"PersonID":"12345678901"},"Doctor":{"appointment":[],"Appointment":[],"PName":"Marko","Surname":"Pantelic","Email":"pantela@zdravo.com","DateOfBirth":"2021-03-28T17:39:40.5105922+02:00","PhoneNumber":"063/789789","Username":"pantela","ParentsName":"Jovo","MaritalStatus":1,"Gender":0,"Address":null,"PersonID":null},"StartTime":"2021-03-30T12:00:00Z","Duration":30,"PeriodType":0}],"RoomType":0,"Id":101,"Name":"soba za pregled - 1","Avaliabe":true,"AvaliableText":"Yes","RoomTypeText":"Appointment","Equipment":[]},"Doctor":{"appointment":[],"Appointment":[],"PName":"Marko","Surname":"Pantelic","Email":"pantela@zdravo.com","DateOfBirth":"2021-03-28T17:46:35.3545617+02:00","PhoneNumber":"063/789789","Username":"pantela","ParentsName":"Jovo","MaritalStatus":1,"Gender":0,"Address":null,"PersonID":null},"AppointmentRoom":{"appointment":[{"patient":{"appointment":[],"operation":[],"IsGuest":false,"HealthCardNumber":"12123434","Appointment":[],"Operation":[],"PName":"Dejan","Surname":"Bodiroga","Email":"boga@zdravo.com","DateOfBirth":"2021-03-28T17:39:40.5116867+02:00","PhoneNumber":"063/789789","Username":"bogi","ParentsName":"Sale","MaritalStatus":1,"Gender":0,"Address":null,"PersonID":"12345678901"},"doctor":{"appointment":[],"Appointment":[],"PName":"Marko","Surname":"Pantelic","Email":"pantela@zdravo.com","DateOfBirth":"2021-03-28T17:39:40.5105922+02:00","PhoneNumber":"063/789789","Username":"pantela","ParentsName":"Jovo","MaritalStatus":1,"Gender":0,"Address":null,"PersonID":null},"Patient":{"appointment":[],"operation":[],"IsGuest":false,"HealthCardNumber":"12123434","Appointment":[],"Operation":[],"PName":"Dejan","Surname":"Bodiroga","Email":"boga@zdravo.com","DateOfBirth":"2021-03-28T17:39:40.5116867+02:00","PhoneNumber":"063/789789","Username":"bogi","ParentsName":"Sale","MaritalStatus":1,"Gender":0,"Address":null,"PersonID":"12345678901"},"Doctor":{"appointment":[],"Appointment":[],"PName":"Marko","Surname":"Pantelic","Email":"pantela@zdravo.com","DateOfBirth":"2021-03-28T17:39:40.5105922+02:00","PhoneNumber":"063/789789","Username":"pantela","ParentsName":"Jovo","MaritalStatus":1,"Gender":0,"Address":null,"PersonID":null},"StartTime":"2021-03-30T12:00:00Z","Duration":30,"PeriodType":0}],"equipment":[],"Appointment":[{"patient":{"appointment":[],"operation":[],"IsGuest":false,"HealthCardNumber":"12123434","Appointment":[],"Operation":[],"PName":"Dejan","Surname":"Bodiroga","Email":"boga@zdravo.com","DateOfBirth":"2021-03-28T17:39:40.5116867+02:00","PhoneNumber":"063/789789","Username":"bogi","ParentsName":"Sale","MaritalStatus":1,"Gender":0,"Address":null,"PersonID":"12345678901"},"doctor":{"appointment":[],"Appointment":[],"PName":"Marko","Surname":"Pantelic","Email":"pantela@zdravo.com","DateOfBirth":"2021-03-28T17:39:40.5105922+02:00","PhoneNumber":"063/789789","Username":"pantela","ParentsName":"Jovo","MaritalStatus":1,"Gender":0,"Address":null,"PersonID":null},"Patient":{"appointment":[],"operation":[],"IsGuest":false,"HealthCardNumber":"12123434","Appointment":[],"Operation":[],"PName":"Dejan","Surname":"Bodiroga","Email":"boga@zdravo.com","DateOfBirth":"2021-03-28T17:39:40.5116867+02:00","PhoneNumber":"063/789789","Username":"bogi","ParentsName":"Sale","MaritalStatus":1,"Gender":0,"Address":null,"PersonID":"12345678901"},"Doctor":{"appointment":[],"Appointment":[],"PName":"Marko","Surname":"Pantelic","Email":"pantela@zdravo.com","DateOfBirth":"2021-03-28T17:39:40.5105922+02:00","PhoneNumber":"063/789789","Username":"pantela","ParentsName":"Jovo","MaritalStatus":1,"Gender":0,"Address":null,"PersonID":null},"StartTime":"2021-03-30T12:00:00Z","Duration":30,"PeriodType":0}],"RoomType":0,"Id":101,"Name":"soba za pregled - 1","Avaliabe":true,"AvaliableText":"Yes","RoomTypeText":"Appointment","Equipment":[]},"StartTime":"2021-04-07T12:00:00Z","Duration":30,"PeriodType":0}],"Operation":[],"PName":"Dejan","Surname":"Bodiroga","Email":"boga@zdravo.com","DateOfBirth":"2021-03-28T17:46:35.355947+02:00","PhoneNumber":"063/789789","Username":"bogi","ParentsName":"Sale","MaritalStatus":1,"Gender":0,"Address":null,"PersonID":"12345678901"}}